{"id": "26db00d9-e80f-4caf-b94f-3e05cfb0f5b7", "company_name": "Samsung Electronics ", "pan": "AADRV6789J", "gstin": "29fdfddcdfdcds", "cin": "U232456788655665", "ucso_data": {"ucso_version": 1, "applicant": {"company_name": "Samsung Electronics ", "pan": "AADRV6789J", "gstin": "29fdfddcdfdcds", "cin": "U232456788655665", "loan_amount_requested": 50000000.0, "loan_purpose": "", "industry_sector": "", "promoter_name": "Utkarsh Singh", "promoter_din": "", "years_in_business": 0, "annual_turnover": 0, "existing_bank_loans": 0, "collateral_offered": "", "contact_email": ""}, "compliance": {"status": "PENDING", "missing_documents": [], "checked_at": ""}, "documents": {"files": [{"doc_id": "ANNUAL_REPORT_9e0141c2-8dc7-4e33-a08b-84107ca648ca", "type": "ANNUAL_REPORT", "storage_path": "26db00d9-e80f-4caf-b94f-3e05cfb0f5b7/ANNUAL_REPORT/2024_con_quarter01_all (1).pdf", "file_url": "local://26db00d9-e80f-4caf-b94f-3e05cfb0f5b7/ANNUAL_REPORT/2024_con_quarter01_all (1).pdf", "filename": "2024_con_quarter01_all (1).pdf", "s3_key": "26db00d9-e80f-4caf-b94f-3e05cfb0f5b7/ANNUAL_REPORT/2024_con_quarter01_all (1).pdf", "parsed": false, "confidence": 0.0, "uploaded_at": "2026-04-13T09:53:13.919864+00:00", "doc_type": "ANNUAL_REPORT"}, {"doc_id": "BANK_STMT_9e0141c2-8dc7-4e33-a08b-84107ca648ca", "type": "BANK_STMT", "storage_path": "26db00d9-e80f-4caf-b94f-3e05cfb0f5b7/ANNUAL_REPORT/2024_con_quarter01_all (1).pdf", "file_url": "local://26db00d9-e80f-4caf-b94f-3e05cfb0f5b7/ANNUAL_REPORT/2024_con_quarter01_all (1).pdf", "filename": "2024_con_quarter01_all (1).pdf", "s3_key": "26db00d9-e80f-4caf-b94f-3e05cfb0f5b7/ANNUAL_REPORT/2024_con_quarter01_all (1).pdf", "parsed": false, "confidence": 0.0, "uploaded_at": "2026-04-13T09:53:13.919864+00:00", "doc_type": "BANK_STMT"}, {"doc_id": "GST_RETURN_9e0141c2-8dc7-4e33-a08b-84107ca648ca", "type": "GST_RETURN", "storage_path": "26db00d9-e80f-4caf-b94f-3e05cfb0f5b7/ANNUAL_REPORT/2024_con_quarter01_all (1).pdf", "file_url": "local://26db00d9-e80f-4caf-b94f-3e05cfb0f5b7/ANNUAL_REPORT/2024_con_quarter01_all (1).pdf", "filename": "2024_con_quarter01_all (1).pdf", "s3_key": "26db00d9-e80f-4caf-b94f-3e05cfb0f5b7/ANNUAL_REPORT/2024_con_quarter01_all (1).pdf", "parsed": false, "confidence": 0.0, "uploaded_at": "2026-04-13T09:53:13.919864+00:00", "doc_type": "GST_RETURN"}, {"doc_id": "ITR_9e0141c2-8dc7-4e33-a08b-84107ca648ca", "type": "ITR", "storage_path": "26db00d9-e80f-4caf-b94f-3e05cfb0f5b7/ANNUAL_REPORT/2024_con_quarter01_all (1).pdf", "file_url": "local://26db00d9-e80f-4caf-b94f-3e05cfb0f5b7/ANNUAL_REPORT/2024_con_quarter01_all (1).pdf", "filename": "2024_con_quarter01_all (1).pdf", "s3_key": "26db00d9-e80f-4caf-b94f-3e05cfb0f5b7/ANNUAL_REPORT/2024_con_quarter01_all (1).pdf", "parsed": false, "confidence": 0.0, "uploaded_at": "2026-04-13T09:53:13.919864+00:00", "doc_type": "ITR"}]}, "financials": {}, "derived_features": {}, "gst_analysis": {"reconciliation_status": "PENDING"}, "bank_reconciliation": {"reconciliation_verdict": "PENDING"}, "mca_intelligence": {"company_status": "UNKNOWN"}, "pan_intelligence": {"status": "PENDING"}, "web_intel": {}, "pd_intelligence": {}, "risk": {"band": "PENDING", "decision": "PENDING"}, "bias_checks": {"counterfactual_tested": false}, "stress_results": {"scenarios": [], "survival_verdict": "PENDING"}, "ews_monitoring": {"enabled": false}, "decision_confidence": {}, "cam_output": {}, "human_notes": {"notes": []}, "audit_log": {"entries": [{"timestamp": "2026-04-13T09:53:13.970998+00:00", "application_id": "26db00d9-e80f-4caf-b94f-3e05cfb0f5b7", "agent": "monitor-agent", "event": "health_check", "alerts": [], "alert_count": 0}], "latest_check": {"timestamp": "2026-04-13T09:53:13.970998+00:00", "application_id": "26db00d9-e80f-4caf-b94f-3e05cfb0f5b7", "agent": "monitor-agent", "event": "health_check", "alerts": [], "alert_count": 0}, "alert_count": 0}, "application_id": "26db00d9-e80f-4caf-b94f-3e05cfb0f5b7"}, "status": "CREATED", "created_at": "2026-04-13T09:52:45.963809+00:00", "updated_at": "2026-04-13T09:53:13.984579+00:00"}